fetchrunner/__init__.py
fetchrunner/config.py
fetchrunner/fetcher.py
fetchrunner/formatting.py
fetchrunner/io.py
fetchrunner/main.py
fetchrunner/utils.py
fetchrunner-0.1.0.dist-info/METADATA
fetchrunner-0.1.0.dist-info/WHEEL
fetchrunner-0.1.0.dist-info/entry_points.txt
fetchrunner-0.1.0.dist-info/top_level.txt
fetchrunner-0.1.0.dist-info/RECORD
