Metadata-Version: 2.1
Name: fetchrunner
Version: 0.1.0
Summary: A CLI tool to fetch running race information from Kikourou website.
Author: Arnaud Trog
Project-URL: Homepage, https://github.com/Arnautt/fetchrunner
Project-URL: Repository, https://github.com/Arnautt/fetchrunner.git
Requires-Python: >=3.12
Requires-Dist: pandas==2.2.2
Requires-Dist: beautifulsoup4==4.12.3
Requires-Dist: requests==2.32.3
Requires-Dist: loguru==0.7.2
Requires-Dist: colorama==0.4.6
Requires-Dist: pyfiglet==1.0.2
